cleval/__init__.py
cleval/arg_parser.py
cleval/box_types.py
cleval/data.py
cleval/eval_functions.py
cleval/main.py
cleval/torchmetric.py
cleval/utils.py
cleval/validation.py
tests/__init__.py
tests/test_scores.py
cleval-0.1.1.dist-info/LICENSE
cleval-0.1.1.dist-info/METADATA
cleval-0.1.1.dist-info/NOTICE
cleval-0.1.1.dist-info/WHEEL
cleval-0.1.1.dist-info/entry_points.txt
cleval-0.1.1.dist-info/top_level.txt
cleval-0.1.1.dist-info/RECORD
