Metadata-Version: 2.1
Name: cleval
Version: 0.1.1
Summary: cleval
Home-page: https://oss.navercorp.com/CLOVA-AI-OCR/cleval
Author: dong.hyun
Author-email: dong.hyun@navercorp.com
Classifier: Programming Language :: Python :: 3
Classifier: License :: OSI Approved :: MIT License
Classifier: Operating System :: OS Independent
Requires-Python: >=3.7
License-File: LICENSE
License-File: NOTICE
Requires-Dist: bottle
Requires-Dist: requests
Requires-Dist: Pillow
Requires-Dist: Polygon3
Requires-Dist: Shapely
Requires-Dist: tqdm
Requires-Dist: pprofile
Requires-Dist: numba >=0.58.0
Requires-Dist: six
Requires-Dist: torchmetrics >=1.2.0
Requires-Dist: numpy
